AUTHORS.rst
CONTRIBUTING.rst
HISTORY.rst
LICENSE
MANIFEST.in
README.rst
setup.cfg
setup.py
bin/PTAdemo_double_metronome
bin/PTAdemo_single_metronome
demo_data/m184b.txt
demo_data/m208a.txt
demo_data/m208a184b.txt
docs/Makefile
docs/PTAdemo.rst
docs/authors.rst
docs/conf.py
docs/contributing.rst
docs/history.rst
docs/index.rst
docs/installation.rst
docs/make.bat
docs/modules.rst
docs/readme.rst
docs/tabletop_pta.rst
docs/usage.rst
docs/PTAdemo_files/PTAdemo_11_0.png
docs/PTAdemo_files/PTAdemo_15_0.png
docs/PTAdemo_files/PTAdemo_17_1.png
docs/PTAdemo_files/PTAdemo_23_0.png
docs/PTAdemo_files/PTAdemo_27_0.png
docs/PTAdemo_files/PTAdemo_29_0.png
docs/PTAdemo_files/PTAdemo_7_0.png
docs/PTAdemo_files/PTAdemo_9_1.png
docs/_build/doctrees/nbsphinx/_static_PTAdemo_11_0.png
docs/_build/doctrees/nbsphinx/_static_PTAdemo_15_0.png
docs/_build/doctrees/nbsphinx/_static_PTAdemo_17_1.png
docs/_build/doctrees/nbsphinx/_static_PTAdemo_23_0.png
docs/_build/doctrees/nbsphinx/_static_PTAdemo_27_0.png
docs/_build/doctrees/nbsphinx/_static_PTAdemo_29_0.png
docs/_build/doctrees/nbsphinx/_static_PTAdemo_7_0.png
docs/_build/doctrees/nbsphinx/_static_PTAdemo_9_1.png
docs/_build/html/_images/PTAdemo_11_0.png
docs/_build/html/_images/PTAdemo_15_0.png
docs/_build/html/_images/PTAdemo_17_1.png
docs/_build/html/_images/PTAdemo_23_0.png
docs/_build/html/_images/PTAdemo_27_0.png
docs/_build/html/_images/PTAdemo_29_0.png
docs/_build/html/_images/PTAdemo_7_0.png
docs/_build/html/_images/PTAdemo_9_1.png
docs/_build/html/_images/_static_PTAdemo_11_0.png
docs/_build/html/_images/_static_PTAdemo_15_0.png
docs/_build/html/_images/_static_PTAdemo_17_1.png
docs/_build/html/_images/_static_PTAdemo_23_0.png
docs/_build/html/_images/_static_PTAdemo_27_0.png
docs/_build/html/_images/_static_PTAdemo_29_0.png
docs/_build/html/_images/_static_PTAdemo_7_0.png
docs/_build/html/_images/_static_PTAdemo_9_1.png
docs/_build/html/_static/ajax-loader.gif
docs/_build/html/_static/comment-bright.png
tabletop_pta.egg-info/PKG-INFO
tabletop_pta.egg-info/SOURCES.txt
tabletop_pta.egg-info/dependency_links.txt
tabletop_pta.egg-info/not-zip-safe
tabletop_pta.egg-info/requires.txt
tabletop_pta.egg-info/top_level.txt
