Metadata-Version: 1.1
Name: tabletop-pta
Version: 0.1.0
Summary: Python Package to do Time of Arrival calculations for a Pulsar Timing Array demmo with metronomes.
Home-page: https://github.com/nanograv/tabletop_pta
Author: Jeffrey Shafiq Hazboun
Author-email: jeffrey.hazboun@nanograv.org
License: MIT license
Keywords: tabletop_pta
Platform: UNKNOWN
Classifier: Development Status :: 2 - Pre-Alpha
Classifier: Intended Audience :: Developers
Classifier: License :: OSI Approved :: MIT License
Classifier: Natural Language :: English
Classifier: Programming Language :: Python :: 2
Classifier: Programming Language :: Python :: 2.7
Classifier: Programming Language :: Python :: 3
Classifier: Programming Language :: Python :: 3.4
Classifier: Programming Language :: Python :: 3.5
Classifier: Programming Language :: Python :: 3.6
